LICENSE
MANIFEST.in
README.md
requirements.txt
setup.py
imfits/__init__.py
imfits/_imfits.py
imfits/au.py
imfits/deprojection.py
imfits/drawmaps.py
imfits/fitfuncs.py
imfits/iu.py
imfits/mapunit.py
imfits.egg-info/PKG-INFO
imfits.egg-info/SOURCES.txt
imfits.egg-info/dependency_links.txt
imfits.egg-info/requires.txt
imfits.egg-info/top_level.txt