Metadata-Version: 2.1
Name: imfits
Version: 2.3.4
Summary: Read and handle fits files for astronomy easily.
Home-page: https://github.com/jinshisai/imfits
Author: Jinshi Sai
Author-email: jn.insa.sai@gmail.com
Classifier: Programming Language :: Python :: 3
Classifier: License :: OSI Approved :: MIT License
Classifier: Operating System :: OS Independent
License-File: LICENSE
